python_webp-2.0.1.dist-info/METADATA
python_webp-2.0.1.dist-info/WHEEL
python_webp-2.0.1.dist-info/entry_points.txt
python_webp/VERSION
python_webp/__init__.py
python_webp/__main__.py
python_webp/__version__.py
python_webp/_logging.py
python_webp/_settings.py
python_webp/cli.py
python_webp/converter.py
python_webp/exceptions.py
python_webp-2.0.1.dist-info/RECORD
