Metadata-Version: 2.1
Name: python-webp
Version: 2.0.1
Summary: Python Image to WEBP
Author-Email: Gabriel <gabrieltkdnobrega63@gmail.com>
License: MIT
Project-URL: Repository, https://github.com/biellSilva/python-webp
Requires-Python: >=3.11
Requires-Dist: pillow>=11.0.0
Requires-Dist: typer>=0.14.0
